HowtodoinjavaQitaJiaocheng2Chuyi/README.md
HowtodoinjavaQitaJiaocheng2Chuyi/__init__.py
HowtodoinjavaQitaJiaocheng2Chuyi/__main__.py
HowtodoinjavaQitaJiaocheng2Chuyi/file.epub
HowtodoinjavaQitaJiaocheng2Chuyi/index.html
HowtodoinjavaQitaJiaocheng2Chuyi/css/__init__.py
HowtodoinjavaQitaJiaocheng2Chuyi/css/annotations.css
HowtodoinjavaQitaJiaocheng2Chuyi/css/main.css
HowtodoinjavaQitaJiaocheng2Chuyi/css/normalize.css
HowtodoinjavaQitaJiaocheng2Chuyi/css/popup.css
HowtodoinjavaQitaJiaocheng2Chuyi/font/__init__.py
HowtodoinjavaQitaJiaocheng2Chuyi/font/fontello.eot
HowtodoinjavaQitaJiaocheng2Chuyi/font/fontello.svg
HowtodoinjavaQitaJiaocheng2Chuyi/font/fontello.ttf
HowtodoinjavaQitaJiaocheng2Chuyi/font/fontello.woff
HowtodoinjavaQitaJiaocheng2Chuyi/img/__init__.py
HowtodoinjavaQitaJiaocheng2Chuyi/img/annotator-glyph-sprite.png
HowtodoinjavaQitaJiaocheng2Chuyi/img/annotator-icon-sprite.png
HowtodoinjavaQitaJiaocheng2Chuyi/img/apple-touch-icon.png
HowtodoinjavaQitaJiaocheng2Chuyi/img/cancelfullscreen.png
HowtodoinjavaQitaJiaocheng2Chuyi/img/close.png
HowtodoinjavaQitaJiaocheng2Chuyi/img/fullscreen.png
HowtodoinjavaQitaJiaocheng2Chuyi/img/loader.gif
HowtodoinjavaQitaJiaocheng2Chuyi/img/menu-icon.png
HowtodoinjavaQitaJiaocheng2Chuyi/img/save.png
HowtodoinjavaQitaJiaocheng2Chuyi/img/saved.png
HowtodoinjavaQitaJiaocheng2Chuyi/img/settings-s.png
HowtodoinjavaQitaJiaocheng2Chuyi/img/settings.png
HowtodoinjavaQitaJiaocheng2Chuyi/img/star.png
HowtodoinjavaQitaJiaocheng2Chuyi/js/__init__.py
HowtodoinjavaQitaJiaocheng2Chuyi/js/epub.js
HowtodoinjavaQitaJiaocheng2Chuyi/js/epub.min.js
HowtodoinjavaQitaJiaocheng2Chuyi/js/epub.min.map
HowtodoinjavaQitaJiaocheng2Chuyi/js/hooks.min.js
HowtodoinjavaQitaJiaocheng2Chuyi/js/hooks.min.map
HowtodoinjavaQitaJiaocheng2Chuyi/js/reader.js
HowtodoinjavaQitaJiaocheng2Chuyi/js/reader.js.map
HowtodoinjavaQitaJiaocheng2Chuyi/js/reader.min.js
HowtodoinjavaQitaJiaocheng2Chuyi/js/reader.min.map
HowtodoinjavaQitaJiaocheng2Chuyi/js/hooks/__init__.py
howtodoinjava_qita_jiaocheng_2_chuyi-2024.3.4.0.dist-info/METADATA
howtodoinjava_qita_jiaocheng_2_chuyi-2024.3.4.0.dist-info/WHEEL
howtodoinjava_qita_jiaocheng_2_chuyi-2024.3.4.0.dist-info/entry_points.txt
howtodoinjava_qita_jiaocheng_2_chuyi-2024.3.4.0.dist-info/top_level.txt
howtodoinjava_qita_jiaocheng_2_chuyi-2024.3.4.0.dist-info/RECORD
